MANIFEST.in
README.txt
requirements.txt
setup.py
oldfashion/__init__.py
oldfashion/argparse_actions.py
oldfashion/command_line.py
oldfashion/dokker.py
oldfashion/oldfashion.py
oldfashion/utils.py
oldfashion.egg-info/PKG-INFO
oldfashion.egg-info/SOURCES.txt
oldfashion.egg-info/dependency_links.txt
oldfashion.egg-info/entry_points.txt
oldfashion.egg-info/requires.txt
oldfashion.egg-info/top_level.txt
oldfashion/builders/.DS_Store
oldfashion/builders/django/.DS_Store
oldfashion/builders/django/.dockerignore
oldfashion/builders/django/Dockerfile
oldfashion/builders/django/nginx-app.conf
oldfashion/builders/django/supervisor-app.conf
oldfashion/builders/django/uwsgi.ini
oldfashion/builders/nodejs/.dockerignore
oldfashion/builders/nodejs/Dockerfile