Metadata-Version: 1.1
Name: oldfashion
Version: 1.0.0
Summary: oldfashion host
Home-page: UNKNOWN
Author: Platon Korzh
Author-email: platon@korzh.io
License: UNKNOWN
Platform: UNKNOWN
Classifier: Development Status :: 2 - Pre-Alpha
Classifier: Intended Audience :: Developers
